sqliteschema/__init__.py
sqliteschema/__main__.py
sqliteschema/__version__.py
sqliteschema/_const.py
sqliteschema/_error.py
sqliteschema/_extractor.py
sqliteschema/_schema.py
sqliteschema/py.typed
sqliteschema/_logger/__init__.py
sqliteschema/_logger/_logger.py
sqliteschema/_logger/_null_logger.py
sqliteschema-2.0.0.dist-info/LICENSE
sqliteschema-2.0.0.dist-info/METADATA
sqliteschema-2.0.0.dist-info/WHEEL
sqliteschema-2.0.0.dist-info/top_level.txt
sqliteschema-2.0.0.dist-info/RECORD
