Metadata-Version: 2.1
Name: sqliteschema
Version: 2.0.0
Summary: A Python library to dump table schema of a SQLite database file.
Home-page: https://github.com/thombashi/sqliteschema
Author: Tsuyoshi Hombashi
Author-email: tsuyoshi.hombashi@gmail.com
License: MIT License
Project-URL: Changlog, https://github.com/thombashi/sqliteschema/releases
Project-URL: Source, https://github.com/thombashi/sqliteschema
Project-URL: Tracker, https://github.com/thombashi/sqliteschema/issues
Keywords: SQLite,library,schema
Classifier: Development Status :: 5 - Production/Stable
Classifier: Environment :: Console
Classifier: Intended Audience :: Developers
Classifier: Intended Audience :: Information Technology
Classifier: License :: OSI Approved :: MIT License
Classifier: Operating System :: OS Independent
Classifier: Programming Language :: Python :: 3
Classifier: Programming Language :: Python :: 3.7
Classifier: Programming Language :: Python :: 3.8
Classifier: Programming Language :: Python :: 3.9
Classifier: Programming Language :: Python :: 3.10
Classifier: Programming Language :: Python :: 3.11
Classifier: Programming Language :: Python :: 3.12
Classifier: Programming Language :: Python :: 3 :: Only
Classifier: Programming Language :: Python :: Implementation :: CPython
Classifier: Programming Language :: Python :: Implementation :: PyPy
Classifier: Topic :: Software Development :: Libraries
Classifier: Topic :: Software Development :: Libraries :: Python Modules
Classifier: Topic :: Database
Classifier: Topic :: Terminals
Requires-Python: >=3.7
License-File: LICENSE
Requires-Dist: mbstrdecoder<2,>=0.8.3
Requires-Dist: tabledata<2,>=1.3.1
Requires-Dist: typepy<2,>=1.1.4
Provides-Extra: cli
Requires-Dist: pytablewriter<2,>=0.64.0; extra == "cli"
Requires-Dist: loguru<1,>=0.4.1; extra == "cli"
Provides-Extra: dumps
Requires-Dist: pytablewriter<2,>=0.64.0; extra == "dumps"
Provides-Extra: logging
Requires-Dist: loguru<1,>=0.4.1; extra == "logging"
Provides-Extra: test
Requires-Dist: pytest>=6.0.1; extra == "test"
Requires-Dist: pytablewriter<2,>=0.64.0; extra == "test"
Requires-Dist: pytest-md-report>=0.5.0; extra == "test"
Requires-Dist: SimpleSQLite>=1.3.2; extra == "test"
Requires-Dist: pytest-discord>=0.1.6; extra == "test"
